AUTHORS
CHANGELOG
INSTALL
LICENSE
MANIFEST.in
README
VERSION
setup.py
test-requirements.txt
insight_reloaded/__init__.py
insight_reloaded/api.py
insight_reloaded/fake_callback.py
insight_reloaded/insight_monitoring.py
insight_reloaded/insight_settings.py
insight_reloaded/preview.py
insight_reloaded/settings_old.py
insight_reloaded/utils.py
insight_reloaded/worker.py
insight_reloaded.egg-info/PKG-INFO
insight_reloaded.egg-info/SOURCES.txt
insight_reloaded.egg-info/dependency_links.txt
insight_reloaded.egg-info/entry_points.txt
insight_reloaded.egg-info/not-zip-safe
insight_reloaded.egg-info/requires.txt
insight_reloaded.egg-info/top_level.txt
insight_reloaded/storage/__init__.py
insight_reloaded/storage/cloudfiles.py
insight_reloaded/storage/file_system.py
insight_reloaded/storage/s3.py
insight_reloaded/tests/__init__.py
insight_reloaded/tests/test.pdf
insight_reloaded/tests/test_api.py
insight_reloaded/tests/test_backends.py