Metadata-Version: 1.1
Name: insight-reloaded
Version: 1.6.4
Summary: 
Home-page: https://github.com/novapost/insight-reloaded
Author: Rémy HUBSCHER
Author-email: remy.hubscher@novapost.fr
License: BSD Licence
Platform: UNKNOWN
Classifier: Programming Language :: Python
Classifier: License :: OSI Approved :: BSD License
